envkernel.py
envkernel-1.1.0.dist-info/LICENSE
envkernel-1.1.0.dist-info/METADATA
envkernel-1.1.0.dist-info/WHEEL
envkernel-1.1.0.dist-info/entry_points.txt
envkernel-1.1.0.dist-info/top_level.txt
envkernel-1.1.0.dist-info/RECORD
