Metadata-Version: 2.1
Name: envkernel
Version: 1.1.0
Summary: Jupyter kernels manipulation and in other environments (docker, Lmod, etc.)
Home-page: https://github.com/NordicHPC/envkernel
Author: Richard Darst
Author-email: rkd@zgib.net
License: UNKNOWN
Keywords: jupyter kernelspec
Platform: UNKNOWN
Classifier: Programming Language :: Python :: 3
Classifier: License :: OSI Approved :: MIT License
Classifier: Operating System :: OS Independent
Classifier: Development Status :: 4 - Beta
Classifier: Framework :: Jupyter
Classifier: Environment :: Console
Classifier: Intended Audience :: System Administrators
Classifier: Intended Audience :: Developers
Classifier: Intended Audience :: Science/Research
Requires-Python: >=3.5
License-File: LICENSE
